gdplib/__init__.py
gdplib/biofuel/__init__.py
gdplib/biofuel/model.py
gdplib/gdp_col/__init__.py
gdplib/gdp_col/column.py
gdplib/gdp_col/fenske.py
gdplib/gdp_col/initialize.py
gdplib/gdp_col/main.py
gdplib/logical/__init__.py
gdplib/logical/positioning.py
gdplib/logical/spectralog.py
gdplib/mod_hens/__init__.py
gdplib/mod_hens/cafaro_approx.py
gdplib/mod_hens/common.py
gdplib/mod_hens/conventional.py
gdplib/mod_hens/modular_discrete.py
gdplib/mod_hens/modular_discrete_single_module.py
gdplib/mod_hens/modular_integer.py
gdplib/modprodnet/__init__.py
gdplib/modprodnet/distributed.py
gdplib/modprodnet/model.py
gdplib/modprodnet/quarter_distributed.py
gdplib/pyomo_examples/__init__.py
gdplib/pyomo_examples/batch_processing.py
gdplib/pyomo_examples/disease_model.py
gdplib/pyomo_examples/jobshop.py
gdplib/pyomo_examples/med_term_purchasing.py
gdplib/stranded_gas/__init__.py
gdplib/stranded_gas/model.py
gdplib/stranded_gas/util.py
gdplib/syngas/__init__.py
gdplib/syngas/syngas_adapted.py
gdplib-20.6.2.dist-info/LICENSE
gdplib-20.6.2.dist-info/METADATA
gdplib-20.6.2.dist-info/WHEEL
gdplib-20.6.2.dist-info/top_level.txt
gdplib-20.6.2.dist-info/RECORD
