Metadata-Version: 2.1
Name: gdplib
Version: 20.6.2
Summary: GDPlib open source model library for Generalized Disjunctive Programming
Home-page: https://github.com/grossmann-group/gdplib
Author: Qi Chen
Author-email: qichen@andrew.cmu.edu
Maintainer: Qi Chen
License: BSD 3-clause
Keywords: pyomo,generalized disjunctive programming
Platform: UNKNOWN
Classifier: Programming Language :: Python :: 3.6
Classifier: Development Status :: 4 - Beta
Classifier: Intended Audience :: Developers
Classifier: License :: OSI Approved :: BSD License
Classifier: Operating System :: OS Independent
Classifier: Topic :: Software Development :: Libraries :: Python Modules
